<?xml version="1.0" encoding="utf-8"?>
<Resource>
	<Version>2</Version>
	<SMaterialData>
		<Root>
			<Sub/>
			<Entity type="SMaterialData">
				<name/>
				<info>
					<Layers count="1" ordered="true">
						<Element index="0">
							<LayerName>745b30f3-9985-4784-bd68-3e2742181d39</LayerName>
							<ShaderName>c5c7cfa0-a62d-416d-b1fc-4a598ee8732e</ShaderName>
							<Parameters count="3" ordered="true">
								<Element index="0">
									<Name>tBaseMap</Name>
									<Value>8059ec80-6567-4f08-8fb3-d872c9aa2d12</Value>
								</Element>
								<Element index="1">
									<Name>tNormalMap</Name>
									<Value>1f934c56-f796-497b-a5ee-934ad5b587ca</Value>
								</Element>
								<Element index="2">
									<Name>tMixMap</Name>
									<Value>77d1f9e1-8d51-4dc0-9b88-c83af5dae905</Value>
								</Element>
							</Parameters>
							<MultiPassMaterials count="0" ordered="true"/>
							<MaterialTrans count="0" ordered="true"/>
						</Element>
					</Layers>
					<ExtTech>46526224</ExtTech>
				</info>
				<flags count="1" ordered="true">
					<Element index="0">17</Element>
				</flags>
				<customRenderset count="1" ordered="true">
					<Element index="0">0</Element>
				</customRenderset>
			</Entity>
		</Root>
	</SMaterialData>
</Resource>
