<?xml version="1.0" encoding="utf-8"?>
<Resource>
	<Version>2</Version>
	<SMaterialData>
		<Root>
			<Sub/>
			<Entity type="SMaterialData">
				<name/>
				<info>
					<Layers count="2" ordered="true">
						<Element index="0">
							<LayerName>2f05a03d-bf8b-4505-ba35-8555423aa8b5</LayerName>
							<ShaderName>c5c7cfa0-a62d-416d-b1fc-4a598ee8732e</ShaderName>
							<Parameters count="3" ordered="true">
								<Element index="0">
									<Name>tBaseMap</Name>
									<Value>7a832eab-f077-4f76-947c-a575c86de4c8</Value>
								</Element>
								<Element index="1">
									<Name>tNormalMap</Name>
									<Value>aa981c06-9be3-41ca-a6f4-a400ccf3f9a7</Value>
								</Element>
								<Element index="2">
									<Name>tMixMap</Name>
									<Value>b7e2662c-22a0-432d-a495-6fdcb98f1a92</Value>
								</Element>
							</Parameters>
							<MultiPassMaterials count="0" ordered="true"/>
							<MaterialTrans count="0" ordered="true"/>
						</Element>
						<Element index="1">
							<LayerName>2f05a03d-bf8b-4505-ba35-8555423aa8b5</LayerName>
							<ShaderName>c5c7cfa0-a62d-416d-b1fc-4a598ee8732e</ShaderName>
							<Parameters count="3" ordered="true">
								<Element index="0">
									<Name>tBaseMap</Name>
									<Value>b3f41f87-65a4-46bd-afe9-065d30ac43bb</Value>
								</Element>
								<Element index="1">
									<Name>tNormalMap</Name>
									<Value>d23d67f3-1fb8-4b05-bb6e-39898058e398</Value>
								</Element>
								<Element index="2">
									<Name>tMixMap</Name>
									<Value>7650afc9-ef14-455f-94e3-843f6ec56617</Value>
								</Element>
							</Parameters>
							<MultiPassMaterials count="0" ordered="true"/>
							<MaterialTrans count="0" ordered="true"/>
						</Element>
					</Layers>
					<ExtTech>-1864605680</ExtTech>
				</info>
				<flags count="2" ordered="true">
					<Element index="0">262161</Element>
					<Element index="1">262161</Element>
				</flags>
				<customRenderset count="2" ordered="true">
					<Element index="0">0</Element>
					<Element index="1">0</Element>
				</customRenderset>
			</Entity>
		</Root>
	</SMaterialData>
</Resource>
