<?xml version="1.0" encoding="utf-8"?>
<Resource>
	<Version>8</Version>
	<SRenderMeshData>
		<Root>
			<Sub/>
			<Entity type="SRenderMeshData">
				<VertexFormat count="4">
					<Element index="0">P3F_N4B_T2F_T2F</Element>
					<Element index="1">T4H_B4H</Element>
					<Element index="2">None</Element>
					<Element index="3">None</Element>
				</VertexFormat>
				<VertexCount>427</VertexCount>
				<IndexCount>507</IndexCount>
				<StreamingMask>0</StreamingMask>
				<PrimTopology>Tri_List</PrimTopology>
				<KeepData>false</KeepData>
				<BoundingVolume rawdata="ENcjswYAgD8AAAClBQCAPwYAgD8GAIA/BgAAQA==">(-0.00000003814699334,1.00000067085413047,-0.00000000000000011,1.00000057814699339,1.00000071432181592,1.00000069258797319,2.00000142864363184)</BoundingVolume>
				<BoundingBox rawdata="BQCAvzqxOrMGAIC/BQCAPwYAAEAGAIA/">(-1.00000061629398673,-0.00000004346768565,-1.00000069258797342,1.00000054000000005,2.00000138517594639,1.00000069258797319)</BoundingBox>
				<Streams count="4">
					<Element index="0">
						<StreamSize>13664</StreamSize>
					</Element>
					<Element index="1">
						<StreamSize>6832</StreamSize>
					</Element>
					<Element index="2">
						<StreamSize>0</StreamSize>
					</Element>
					<Element index="3">
						<StreamSize>0</StreamSize>
					</Element>
				</Streams>
				<Indices>
					<StreamSize>1014</StreamSize>
				</Indices>
				<Groups count="1" ordered="true">
					<Element index="0">
						<StartIndex>0</StartIndex>
						<IndicesCount>507</IndicesCount>
						<StartVertex>0</StartVertex>
						<VerticesCount>427</VerticesCount>
						<BoundingVolume rawdata="ENcjswYAgD8AAAClBQCAPwYAgD8GAIA/BgAAQA==">(-0.00000003814699334,1.00000067085413047,-0.00000000000000011,1.00000057814699339,1.00000071432181592,1.00000069258797319,2.00000142864363184)</BoundingVolume>
						<BoundingBox rawdata="BQCAvzqxOrMGAIC/BQCAPwYAAEAGAIA/">(-1.00000061629398673,-0.00000004346768565,-1.00000069258797342,1.00000054000000005,2.00000138517594639,1.00000069258797319)</BoundingBox>
					</Element>
				</Groups>
			</Entity>
		</Root>
	</SRenderMeshData>
</Resource>
